{"name":"yum_dag","version":"0.1.3","description":"Used to create a graph of yum repositories","long_description":"Chef cookbook for creating a directed acyclic graph of yum repositories. I suppose you *could* create a cycle in your graph, but why would you?","maintainer":"Jared Barnett","maintainer_email":"jared.barnett@gmail.com","license":"all_rights","platforms":{},"dependencies":{"yum":"~> 3.10.0","httpd":"~> 0.2"},"recommendations":{},"suggestions":{},"conflicting":{},"providing":{},"replacing":{},"attributes":{},"groupings":{},"recipes":{}}